kuantaz_api_client/Client.py
kuantaz_api_client/KuantazException.py
kuantaz_api_client/RequestHelper.py
kuantaz_api_client/StatisticResult.py
kuantaz_api_client/VerificationResult.py
kuantaz_api_client/__init__.py
kuantaz_api_client-1.0.1.dist-info/METADATA
kuantaz_api_client-1.0.1.dist-info/WHEEL
kuantaz_api_client-1.0.1.dist-info/top_level.txt
kuantaz_api_client-1.0.1.dist-info/RECORD
