Metadata-Version: 2.1
Name: kuantaz-api-client
Version: 1.0.1
Summary: Python API Client to communicate with kzCaptcha.
Author-email: Kuantaz Core Developers <kuantaz@kuantaz.com>
Project-URL: Website, https://kuantaz.com
Keywords: kuantaz,api-client,spam-protection,accessibility,captcha
Classifier: Development Status :: 5 - Production/Stable
Classifier: Intended Audience :: Developers
Classifier: Operating System :: OS Independent
Classifier: Programming Language :: Python :: 3.5
Classifier: Programming Language :: Python :: 3.6
Classifier: Programming Language :: Python :: 3.7
Classifier: Programming Language :: Python :: 3.8
Classifier: Programming Language :: Python :: 3.9
Classifier: Programming Language :: Python :: 3.10
Classifier: Programming Language :: Python :: 3.11
Classifier: Programming Language :: Python :: 3.12
Classifier: Topic :: Internet
Requires-Python: >=3.5
Requires-Dist: requests (>=2.31.0)
Provides-Extra: dev
Requires-Dist: pytest-runner ; extra == 'dev'
Requires-Dist: requests-mock ; extra == 'dev'
Requires-Dist: pip-tools ; extra == 'dev'
